<?xml version="1.0"?>
<dblpperson name="Jing Xu 0005" pid="07/1951-5" n="43">
<person key="homepages/07/1951-5" mdate="2018-08-14">
<author pid="07/1951-5">Jing Xu 0005</author>
<note label="PhD 2011" type="affiliation">Huazhong University of Science and Technology, Department of Electronics and Information Engineering, Wuhan, China</note>
<url>https://orcid.org/0000-0003-4443-1980</url>
</person>
<homonyms n="26">
<h f="x/Xu:Jing"><person publtype="disambiguation" key="homepages/07/1951" mdate="2017-09-29">
<author pid="07/1951">Jing Xu</author>
</person>
</h>
<h f="x/Xu_0001:Jing"><person key="homepages/07/1951-1" mdate="2020-09-18">
<author pid="07/1951-1">Jing Xu 0001</author>
<note type="affiliation">East China Normal University, School of Information Science and Technology, Shanghai, China</note>
<note type="affiliation">Chinese Academy of Sciences, Shanghai Institute of Microsystem and Information Technology, China</note>
<note type="affiliation">Shanghai Research Center for Wireless Communications, Shanghai, China</note>
<note type="affiliation" label="PhD 2005">Southeast University, National Mobile Communications Research Lab, Nanjing, China</note>
<url>https://orcid.org/0000-0002-9911-1581</url>
<url>https://www.researchgate.net/profile/Jing_Xu40</url>
</person>
</h>
<h f="x/Xu_0002:Jing"><person key="homepages/07/1951-2" mdate="2019-05-03">
<author pid="07/1951-2">Jing Xu 0002</author>
<note type="affiliation">Chinese Academy of Sciences, Trusted Computing and Information Assurance Laboratory, Beijing, China</note>
<note label="former" type="affiliation">Chinese Academy of Sciences, State Key Laboratory of Information Security, Beijing, China</note>
<note label="PhD 2002" type="affiliation">Chinese Academy of Sciences, Academy of Mathematics and Systems Science, China</note>
</person>
</h>
<h f="x/Xu_0003:Jing"><person key="homepages/07/1951-3" mdate="2017-10-18">
<author pid="07/1951-3">Jing Xu 0003</author>
<note type="affiliation">Xi'an Jiaotong University, Department of Information and Communications Engineering, China</note>
<url>https://orcid.org/0000-0003-0072-8520</url>
</person>
</h>
<h f="x/Xu_0004:Jing"><person key="homepages/07/1951-4" mdate="2018-01-17">
<author pid="07/1951-4">Jing Xu 0004</author>
<note label="since 2007" type="affiliation">Zhejiang Gongshang University, School of Statistics and Mathematics, Hangzhou, China</note>
<note label="2013 - 2014" type="affiliation">University of California Los Angeles, Department of Mathematics, CA, USA</note>
<note label="2008 - 2009" type="affiliation">Nanyang Technological University, Department of Mathematics, Singapore</note>
<note label="PhD 2007" type="affiliation">Chinese Academy of Sciences, Academy of Mathematics and Systems Science, Beijing, China</note>
<url>https://orcid.org/0000-0002-3946-2056</url>
</person>
</h>
<h f="x/Xu_0006:Jing"><person key="homepages/07/1951-6" mdate="2018-01-19">
<author pid="07/1951-6">Jing Xu 0006</author>
<note type="affiliation">Soochow University, Institute of Intelligent Information Processing and Applications, Suzhou, China</note>
</person>
</h>
<h f="x/Xu_0007:Jing"><person key="homepages/07/1951-7" mdate="2018-02-22">
<author pid="07/1951-7">Jing Xu 0007</author>
<note type="affiliation">University of Science and Technology of China, School of Computer Science and Technology, Hefei, China</note>
<url>https://orcid.org/0000-0002-5154-6236</url>
</person>
</h>
<h f="x/Xu_0008:Jing"><person key="homepages/07/1951-8" mdate="2019-09-04">
<author pid="07/1951-8">Jing Xu 0008</author>
<note label="PhD 2003" type="affiliation">Nankai University, College of Information Technical Science, Tianjin, China</note>
<url>https://orcid.org/0000-0001-8532-2241</url>
</person>
</h>
<h f="x/Xu_0009:Jing"><person key="homepages/07/1951-9" mdate="2019-05-20">
<author pid="07/1951-9">Jing Xu 0009</author>
<note label="PhD 2010" type="affiliation">University of California, Riverside, USA</note>
</person>
</h>
<h f="x/Xu_0010:Jing"><person key="homepages/07/1951-10" mdate="2019-05-20">
<author pid="07/1951-10">Jing Xu 0010</author>
<note label="PhD 2011" type="affiliation">Chinese University of Hong Kong, Hong Kong</note>
</person>
</h>
<h f="x/Xu_0011:Jing"><person key="homepages/07/1951-11" mdate="2020-09-18">
<author pid="07/1951-11">Jing Xu 0011</author>
<note type="affiliation">Tsinghua University, Department of Mechanical Engineering, Beijing Key Laboratory of Precision/Ultra-Precision Manufacturing Equipment Control &#38; State Key Laboratory of Tribology, Beijing, China</note>
<url>http://www.me.tsinghua.edu.cn/en/essay/176/1030.html</url>
<url>https://scholar.google.com/citations?user=36TApxgAAAAJ</url>
<url>https://orcid.org/0000-0002-2997-2351</url>
<url>https://www.researchgate.net/profile/Jing_Xu87</url>
</person>
</h>
<h f="x/Xu_0012:Jing"><person key="homepages/07/1951-12" mdate="2020-07-08">
<author pid="07/1951-12">Jing Xu 0012</author>
<note type="affiliation">Google, Mountain View, CA, USA</note>
<note type="affiliation">VMware, Inc., Palo Alto, CA, USA</note>
<note type="affiliation">Florida International University, Miami, FL, USA</note>
<note label="PhD 2011" type="affiliation">University of Florida, ACIS Lab, Gainesville, FL, USA</note>
<url>https://www.linkedin.com/in/jing-xu-b98b198a?challengeId</url>
</person>
</h>
<h f="x/Xu_0013:Jing"><person key="homepages/07/1951-13" mdate="2020-07-28">
<author pid="07/1951-13">Jing Xu 0013</author>
<note type="affiliation">Jiangsu University of Science and Technology, Marine Equipment and Technology Institute, Zhenjiang, China</note>
<note type="affiliation">China University of Mining &#38; Technology, School of Mechatronic Engineering, Xuzhou, China</note>
</person>
</h>
<h f="x/Xu_0014:Jing"><person key="homepages/07/1951-14" mdate="2020-09-18">
<author pid="07/1951-14">Jing Xu 0014</author>
<note type="uname">&#24464;&#23143;</note>
<note type="affiliation" label="PhD 2016">University of Massachusetts Lowell, Department of Computer Science, Lowell MA, USA</note>
<url>https://rocketreach.co/jing-xu-xu-jing-email_61269828</url>
<url>https://www.researchgate.net/scientific-contributions/2059894081_Jing_Xu</url>
<url>https://www.linkedin.com/in/toxujing</url>
</person>
</h>
<h f="x/Xu_0015:Jing"><person key="homepages/07/1951-15" mdate="2020-09-18">
<author pid="07/1951-15">Jing Xu 0015</author>
<note type="affiliation">East China University of Science and Technology, Key Laboratory of Advanced Control and Optimization for Chemical Process, Shanghai, China</note>
<note type="affiliation" label="PhD 2017">Nanjing University of Science and Technology, School of Automation, Nanjing, China</note>
<url>https://orcid.org/0000-0002-0647-9767</url>
<url>https://www.researchgate.net/profile/Jing_Xu268</url>
</person>
</h>
<h f="x/Xu_0016:Jing"><person key="homepages/07/1951-16" mdate="2020-07-28">
<author pid="07/1951-16">Jing Xu 0016</author>
<note type="affiliation">Northeastern University, School of Mechanical Engineering and Automation, Shenyang, China</note>
<url>https://orcid.org/0000-0001-6257-8770</url>
</person>
</h>
<h f="x/Xu_0017:Jing"><person key="homepages/07/1951-17" mdate="2020-07-09">
<author pid="07/1951-17">Jing Xu 0017</author>
<note type="affiliation">Nanjing University of Aeronautics and Astronautics, College of Computer Science and Technology, Nanjing, China</note>
<url>https://orcid.org/0000-0002-3128-4718</url>
</person>
</h>
<h f="x/Xu_0018:Jing"><person key="homepages/07/1951-18" mdate="2020-08-04">
<author pid="07/1951-18">Jing Xu 0018</author>
<note type="affiliation">Zhejiang A&#38;F University, Department of Optical Engineering, Lin'an, China</note>
<note type="affiliation">Jilin University, Institute of Theoretical Chemistry, Changchun, China</note>
<url>https://orcid.org/0000-0001-5558-6908</url>
<url>https://www.wikidata.org/entity/Q90994444</url>
</person>
</h>
<h f="x/Xu_0019:Jing"><person key="homepages/07/1951-19" mdate="2020-09-18">
<author pid="07/1951-19">Jing Xu 0019</author>
<note type="uname">&#24464;&#38742;</note>
<note type="affiliation">Renmin University of China, School of Finance, Beijing, China</note>
<url>https://sites.google.com/view/jing-xu-homepage/home</url>
<url>https://orcid.org/0000-0002-4352-7756</url>
</person>
</h>
<h f="x/Xu_0020:Jing"><person key="homepages/07/1951-20" mdate="2020-07-28">
<author pid="07/1951-20">Jing Xu 0020</author>
<note type="affiliation">University of California Santa Barbara, Department of Geography, Santa Barbara, CA, USA</note>
<url>https://orcid.org/0000-0003-2892-905X</url>
</person>
</h>
<h f="x/Xu_0021:Jing"><person key="homepages/07/1951-21" mdate="2020-07-09">
<author pid="07/1951-21">Jing Xu 0021</author>
<note type="affiliation">University of Jinan, School of Information Science and Engineering, &#38; Shandong Provincial Key Laboratory of Network Based Intelligent Computing, Jinan, China</note>
<url>https://orcid.org/0000-0002-1039-3309</url>
</person>
</h>
<h f="x/Xu_0022:Jing"><person key="homepages/07/1951-22" mdate="2020-07-28">
<author pid="07/1951-22">Jing Xu 0022</author>
<note type="affiliation">Xidian University, School of Mathematics and Statistics, Xi'an, China</note>
<url>https://orcid.org/0000-0003-3096-6263</url>
</person>
</h>
<h f="x/Xu_0023:Jing"><person key="homepages/07/1951-23" mdate="2020-09-18">
<author pid="07/1951-23">Jing Xu 0023</author>
<note type="affiliation">Capital Normal University, School of Management, Beijing, China</note>
<url>https://orcid.org/0000-0002-6647-0000</url>
<url>https://www.researchgate.net/profile/Jing_Xu157</url>
</person>
</h>
<h f="x/Xu_0024:Jing"><person key="homepages/07/1951-24" mdate="2020-07-28">
<author pid="07/1951-24">Jing Xu 0024</author>
<note label="PhD 2008" type="affiliation">Carleton University, Department of Systems and Computer Engineering, Ottawa, Canada</note>
<url>http://www.sce.carleton.ca/~xujing/</url>
</person>
</h>
<h f="x/Xu_0025:Jing"><person key="homepages/07/1951-25" mdate="2020-07-28">
<author pid="07/1951-25">Jing Xu 0025</author>
<note type="affiliation">Beijing University of Posts and Telecommunications, State Key Laboratory of Networking and Switching Technology, Beijing, China</note>
</person>
</h>
<h f="x/Xu_0026:Jing"><person key="homepages/07/1951-26" mdate="2020-07-28">
<author pid="07/1951-26">Jing Xu 0026</author>
<note type="affiliation">Capital Normal University, Department of Mathematics, Beijing, China</note>
</person>
</h>
</homonyms>
<r><article key="journals/iotj/GongZHXCN20" mdate="2021-04-09">
<author pid="92/3836">Shimin Gong</author>
<author orcid="0000-0002-4976-8171" pid="172/5484">Yuze Zou</author>
<author pid="37/8852">Dinh Thai Hoang</author>
<author pid="07/1951-5">Jing Xu 0005</author>
<author pid="31/1966">Wenqing Cheng</author>
<author orcid="0000-0002-7442-7416" pid="76/440">Dusit Niyato</author>
<title>Capitalizing Backscatter-Aided Hybrid Relay Communications With Wireless Energy Harvesting.</title>
<pages>8709-8721</pages>
<year>2020</year>
<volume>7</volume>
<journal>IEEE Internet Things J.</journal>
<number>9</number>
<ee>https://doi.org/10.1109/JIOT.2020.2995512</ee>
<url>db/journals/iotj/iotj7.html#GongZHXCN20</url>
</article>
</r>
<r><article key="journals/network/GongXXNL20" mdate="2021-04-09">
<author pid="92/3836">Shimin Gong</author>
<author pid="187/0165">Yutong Xie</author>
<author pid="07/1951-5">Jing Xu 0005</author>
<author orcid="0000-0002-7442-7416" pid="76/440">Dusit Niyato</author>
<author pid="98/153">Ying-Chang Liang</author>
<title>Deep Reinforcement Learning for Backscatter-Aided Data Offloading in Mobile Edge Computing.</title>
<pages>106-113</pages>
<year>2020</year>
<volume>34</volume>
<journal>IEEE Netw.</journal>
<number>5</number>
<ee>https://doi.org/10.1109/MNET.001.1900561</ee>
<url>db/journals/network/network34.html#GongXXNL20</url>
</article>
</r>
<r><article key="journals/tccn/XuGZLZN20" mdate="2020-07-03">
<author orcid="0000-0003-4443-1980" pid="07/1951-5">Jing Xu 0005</author>
<author orcid="0000-0003-4874-8766" pid="92/3836">Shimin Gong</author>
<author pid="172/5484">Yuze Zou</author>
<author orcid="0000-0002-2187-8125" pid="49/3283-4">Wei Liu 0004</author>
<author orcid="0000-0003-3279-0695" pid="80/1651-1">Kai Zeng 0001</author>
<author orcid="0000-0002-7442-7416" pid="76/440">Dusit Niyato</author>
<title>Redundant Sniffer Deployment for Multi-Channel Wireless Network Forensics With Unreliable Conditions.</title>
<pages>394-407</pages>
<year>2020</year>
<volume>6</volume>
<journal>IEEE Trans. Cogn. Commun. Netw.</journal>
<number>1</number>
<ee>https://doi.org/10.1109/TCCN.2019.2937487</ee>
<url>db/journals/tccn/tccn6.html#XuGZLZN20</url>
</article>
</r>
<r><article key="journals/tvt/ZouGXCHN20" mdate="2020-12-01">
<author orcid="0000-0002-4976-8171" pid="172/5484">Yuze Zou</author>
<author orcid="0000-0003-4874-8766" pid="92/3836">Shimin Gong</author>
<author orcid="0000-0003-4443-1980" pid="07/1951-5">Jing Xu 0005</author>
<author pid="31/1966">Wenqing Cheng</author>
<author pid="37/8852">Dinh Thai Hoang</author>
<author orcid="0000-0002-7442-7416" pid="76/440">Dusit Niyato</author>
<title>Wireless Powered Intelligent Reflecting Surfaces for Enhancing Wireless Communications.</title>
<pages>12369-12373</pages>
<year>2020</year>
<volume>69</volume>
<journal>IEEE Trans. Veh. Technol.</journal>
<number>10</number>
<ee>https://doi.org/10.1109/TVT.2020.3011942</ee>
<url>db/journals/tvt/tvt69.html#ZouGXCHN20</url>
</article>
</r>
<r><inproceedings key="conf/wcnc/ZouGXCHN20" mdate="2021-04-09">
<author pid="172/5484">Yuze Zou</author>
<author pid="92/3836">Shimin Gong</author>
<author pid="07/1951-5">Jing Xu 0005</author>
<author pid="31/1966">Wenqing Cheng</author>
<author pid="37/8852">Dinh Thai Hoang</author>
<author orcid="0000-0002-7442-7416" pid="76/440">Dusit Niyato</author>
<title>Joint Energy Beamforming and Optimization for Intelligent Reflecting Surface Enhanced Communications.</title>
<pages>1-6</pages>
<year>2020</year>
<booktitle>WCNC Workshops</booktitle>
<ee>https://doi.org/10.1109/WCNCW48565.2020.9124846</ee>
<crossref>conf/wcnc/2020w</crossref>
<url>db/conf/wcnc/wcncw2020.html#ZouGXCHN20</url>
</inproceedings>
</r>
<r><article publtype="informal" key="journals/corr/abs-2001-10180" mdate="2020-01-30">
<author pid="92/3836">Shimin Gong</author>
<author pid="172/5484">Yuze Zou</author>
<author pid="37/8852">Dinh Thai Hoang</author>
<author pid="07/1951-5">Jing Xu 0005</author>
<author pid="31/1966">Wenqing Cheng</author>
<author pid="76/440">Dusit Niyato</author>
<title>Capitalizing Backscatter-Aided Hybrid Relay Communications with Wireless Energy Harvesting.</title>
<year>2020</year>
<volume>abs/2001.10180</volume>
<journal>CoRR</journal>
<ee type="oa">https://arxiv.org/abs/2001.10180</ee>
<url>db/journals/corr/corr2001.html#abs-2001-10180</url>
</article>
</r>
<r><article publtype="informal" key="journals/corr/abs-2001-10183" mdate="2020-07-09">
<author pid="92/3836">Shimin Gong</author>
<author pid="187/0165">Yutong Xie</author>
<author pid="07/1951-5">Jing Xu 0005</author>
<author pid="76/440">Dusit Niyato</author>
<author pid="98/153">Ying-Chang Liang</author>
<title>Deep Reinforcement Learning for Backscatter-Aided Data Offloading in Mobile Edge Computing.</title>
<year>2020</year>
<volume>abs/2001.10183</volume>
<journal>CoRR</journal>
<ee type="oa">https://arxiv.org/abs/2001.10183</ee>
<url>db/journals/corr/corr2001.html#abs-2001-10183</url>
</article>
</r>
<r><article key="journals/iotj/XuLGZN19" mdate="2020-06-08">
<author orcid="0000-0003-4443-1980" pid="07/1951-5">Jing Xu 0005</author>
<author orcid="0000-0003-1076-1738" pid="137/8316">Jiachen Li</author>
<author orcid="0000-0003-4874-8766" pid="92/3836">Shimin Gong</author>
<author orcid="0000-0001-6784-5583" pid="95/1161-1">Kun Zhu 0001</author>
<author orcid="0000-0002-7442-7416" pid="76/440">Dusit Niyato</author>
<title>Passive Relaying Game for Wireless Powered Internet of Things in Backscatter-Aided Hybrid Radio Networks.</title>
<pages>8933-8944</pages>
<year>2019</year>
<volume>6</volume>
<journal>IEEE Internet Things J.</journal>
<number>5</number>
<ee>https://doi.org/10.1109/JIOT.2019.2924977</ee>
<url>db/journals/iotj/iotj6.html#XuLGZN19</url>
</article>
</r>
<r><article key="journals/network/GongXNHH19" mdate="2020-09-11">
<author pid="92/3836">Shimin Gong</author>
<author pid="07/1951-5">Jing Xu 0005</author>
<author orcid="0000-0002-7442-7416" pid="76/440">Dusit Niyato</author>
<author pid="85/2836">Xiaoxia Huang</author>
<author pid="83/514">Zhu Han</author>
<title>Backscatter-Aided Cooperative Relay Communications in Wireless-Powered Hybrid Radio Networks.</title>
<pages>234-241</pages>
<year>2019</year>
<volume>33</volume>
<journal>IEEE Netw.</journal>
<number>5</number>
<ee>https://doi.org/10.1109/MNET.2019.1800335</ee>
<url>db/journals/network/network33.html#GongXNHH19</url>
</article>
</r>
<r><article key="journals/tccn/GongGXGHN19" mdate="2020-07-03">
<author orcid="0000-0003-4874-8766" pid="92/3836">Shimin Gong</author>
<author orcid="0000-0002-0142-1515" pid="92/2834-1">Lin Gao 0001</author>
<author orcid="0000-0003-4443-1980" pid="07/1951-5">Jing Xu 0005</author>
<author orcid="0000-0003-2241-125X" pid="93/10800">Yuanxiong Guo</author>
<author orcid="0000-0002-9528-0863" pid="37/8852">Dinh Thai Hoang</author>
<author orcid="0000-0002-7442-7416" pid="76/440">Dusit Niyato</author>
<title>Exploiting Backscatter-Aided Relay Communications With Hybrid Access Model in Device-to-Device Networks.</title>
<pages>835-848</pages>
<year>2019</year>
<volume>5</volume>
<journal>IEEE Trans. Cogn. Commun. Netw.</journal>
<number>4</number>
<ee>https://doi.org/10.1109/TCCN.2019.2925080</ee>
<url>db/journals/tccn/tccn5.html#GongGXGHN19</url>
</article>
</r>
<r><article key="journals/tcom/XuZGGNC19" mdate="2020-09-01">
<author orcid="0000-0003-4443-1980" pid="07/1951-5">Jing Xu 0005</author>
<author pid="172/5484">Yuze Zou</author>
<author orcid="0000-0003-4874-8766" pid="92/3836">Shimin Gong</author>
<author orcid="0000-0002-0142-1515" pid="92/2834-1">Lin Gao 0001</author>
<author orcid="0000-0002-7442-7416" pid="76/440">Dusit Niyato</author>
<author pid="31/1966">Wenqing Cheng</author>
<title>Robust Transmissions in Wireless-Powered Multi-Relay Networks With Chance Interference Constraints.</title>
<pages>973-987</pages>
<year>2019</year>
<volume>67</volume>
<journal>IEEE Trans. Commun.</journal>
<number>2</number>
<ee>https://doi.org/10.1109/TCOMM.2018.2877466</ee>
<url>db/journals/tcom/tcom67.html#XuZGGNC19</url>
</article>
</r>
<r><inproceedings key="conf/globecom/XieXG0HN19" mdate="2020-07-28">
<author pid="187/0165">Yutong Xie</author>
<author pid="250/1076">Zhengzhuo Xu</author>
<author pid="92/3836">Shimin Gong</author>
<author pid="07/1951-5">Jing Xu 0005</author>
<author pid="37/8852">Dinh Thai Hoang</author>
<author pid="76/440">Dusit Niyato</author>
<title>Backscatter-Assisted Hybrid Relaying Strategy for Wireless Powered IoT Communications.</title>
<pages>1-6</pages>
<year>2019</year>
<booktitle>GLOBECOM</booktitle>
<ee>https://doi.org/10.1109/GLOBECOM38437.2019.9013386</ee>
<crossref>conf/globecom/2019</crossref>
<url>db/conf/globecom/globecom2019.html#XieXG0HN19</url>
</inproceedings>
</r>
<r><inproceedings key="conf/globecom/ZouXGGNC19" mdate="2020-07-28">
<author pid="172/5484">Yuze Zou</author>
<author pid="07/1951-5">Jing Xu 0005</author>
<author pid="92/3836">Shimin Gong</author>
<author orcid="0000-0003-2241-125X" pid="93/10800">Yuanxiong Guo</author>
<author pid="76/440">Dusit Niyato</author>
<author pid="31/1966">Wenqing Cheng</author>
<title>Backscatter-Aided Hybrid Data Offloading for Wireless Powered Edge Sensor Networks.</title>
<pages>1-6</pages>
<year>2019</year>
<booktitle>GLOBECOM</booktitle>
<ee>https://doi.org/10.1109/GLOBECOM38437.2019.9014101</ee>
<crossref>conf/globecom/2019</crossref>
<url>db/conf/globecom/globecom2019.html#ZouXGGNC19</url>
</inproceedings>
</r>
<r><inproceedings key="conf/iccchina/XieXZXGW19" mdate="2019-10-18">
<author pid="187/0165">Yutong Xie</author>
<author pid="250/1076">Zhengzhuo Xu</author>
<author pid="250/1069">Yuxing Zhong</author>
<author pid="07/1951-5">Jing Xu 0005</author>
<author pid="92/3836">Shimin Gong</author>
<author pid="17/221">Yi Wang</author>
<title>Backscatter-Assisted Computation Offloading for Energy Harvesting IoT Devices via Policy-based Deep Reinforcement Learning.</title>
<pages>65-70</pages>
<year>2019</year>
<booktitle>ICCC Workshops</booktitle>
<ee>https://doi.org/10.1109/ICCChinaW.2019.8849964</ee>
<crossref>conf/iccchina/2019w</crossref>
<url>db/conf/iccchina/iccchina2019w.html#XieXZXGW19</url>
</inproceedings>
</r>
<r><inproceedings key="conf/iccnc/ChenLGGX19" mdate="2019-10-18">
<author pid="239/2697">Wenfan Chen</author>
<author pid="27/4942">Chengming Li</author>
<author pid="92/3836">Shimin Gong</author>
<author pid="92/2834-1">Lin Gao 0001</author>
<author pid="07/1951-5">Jing Xu 0005</author>
<title>Joint Transmission Scheduling and Power Allocation in Wirelessly Powered Hybrid Radio Networks.</title>
<pages>515-519</pages>
<year>2019</year>
<booktitle>ICNC</booktitle>
<ee>https://doi.org/10.1109/ICCNC.2019.8685623</ee>
<crossref>conf/iccnc/2019</crossref>
<url>db/conf/iccnc/iccnc2019.html#ChenLGGX19</url>
</inproceedings>
</r>
<r><inproceedings key="conf/pacrim/ZouF0GNC19" mdate="2020-02-11">
<author pid="172/5484">Yuze Zou</author>
<author pid="199/1893">Shaohan Feng</author>
<author pid="07/1951-5">Jing Xu 0005</author>
<author pid="92/3836">Shimin Gong</author>
<author pid="76/440">Dusit Niyato</author>
<author pid="31/1966">Wenqing Cheng</author>
<title>Dynamic Games in Federated Learning Training Service Market.</title>
<pages>1-6</pages>
<year>2019</year>
<booktitle>PACRIM</booktitle>
<ee>https://doi.org/10.1109/PACRIM47961.2019.8985096</ee>
<crossref>conf/pacrim/2019</crossref>
<url>db/conf/pacrim/pacrim2019.html#ZouF0GNC19</url>
</inproceedings>
</r>
<r><inproceedings key="conf/wcnc/Luo0ZG0N19" mdate="2020-03-27">
<author pid="69/7449">Xi Luo</author>
<author pid="07/1951-5">Jing Xu 0005</author>
<author pid="172/5484">Yuze Zou</author>
<author pid="92/3836">Shimin Gong</author>
<author pid="92/2834-1">Lin Gao 0001</author>
<author orcid="0000-0002-7442-7416" pid="76/440">Dusit Niyato</author>
<title>Collaborative Relay Beamforming with Direct Links in Wireless Powered Communications.</title>
<pages>1-6</pages>
<year>2019</year>
<booktitle>WCNC</booktitle>
<ee>https://doi.org/10.1109/WCNC.2019.8886084</ee>
<crossref>conf/wcnc/2019</crossref>
<url>db/conf/wcnc/wcnc2019.html#Luo0ZG0N19</url>
</inproceedings>
</r>
<r><article key="journals/access/XuXLLGZ18" mdate="2019-09-11">
<author orcid="0000-0001-6421-9843" pid="81/4590-5">Wenbo Xu 0005</author>
<author orcid="0000-0003-4443-1980" pid="07/1951-5">Jing Xu 0005</author>
<author pid="137/8316">Jiachen Li</author>
<author pid="49/3283-4">Wei Liu 0004</author>
<author orcid="0000-0003-4874-8766" pid="92/3836">Shimin Gong</author>
<author pid="80/1651-1">Kai Zeng 0001</author>
<title>Robust Spectrum Monitoring in Cognitive Radio Networks With Uncertain Traffic Information.</title>
<pages>34696-34706</pages>
<year>2018</year>
<volume>6</volume>
<journal>IEEE Access</journal>
<ee type="oa">https://doi.org/10.1109/ACCESS.2018.2849726</ee>
<url>db/journals/access/access6.html#XuXLLGZ18</url>
</article>
</r>
<r><article key="journals/tcom/GongHXLWN18" mdate="2020-09-01">
<author orcid="0000-0003-4874-8766" pid="92/3836">Shimin Gong</author>
<author orcid="0000-0001-7092-2041" pid="85/2836">Xiaoxia Huang</author>
<author orcid="0000-0003-4443-1980" pid="07/1951-5">Jing Xu 0005</author>
<author pid="49/3283-4">Wei Liu 0004</author>
<author orcid="0000-0002-1599-5480" pid="37/1304-1">Ping Wang 0001</author>
<author orcid="0000-0002-7442-7416" pid="76/440">Dusit Niyato</author>
<title>Backscatter Relay Communications Powered by Wireless Energy Beamforming.</title>
<pages>3187-3200</pages>
<year>2018</year>
<volume>66</volume>
<journal>IEEE Trans. Commun.</journal>
<number>7</number>
<ee>https://doi.org/10.1109/TCOMM.2018.2809613</ee>
<url>db/journals/tcom/tcom66.html#GongHXLWN18</url>
</article>
</r>
<r><inproceedings key="conf/globecom/LiXGLN18" mdate="2019-07-24">
<author pid="137/8316">Jiachen Li</author>
<author pid="07/1951-5">Jing Xu 0005</author>
<author pid="92/3836">Shimin Gong</author>
<author pid="27/4942">Chengming Li</author>
<author pid="76/440">Dusit Niyato</author>
<title>A Game Theoretic Approach for Backscatter-Aided Relay Communications in Hybrid Radio Networks.</title>
<pages>1-6</pages>
<year>2018</year>
<booktitle>GLOBECOM</booktitle>
<ee>https://doi.org/10.1109/GLOCOM.2018.8647737</ee>
<crossref>conf/globecom/2018</crossref>
<url>db/conf/globecom/globecom2018.html#LiXGLN18</url>
</inproceedings>
</r>
<r><inproceedings key="conf/wcnc/GongXGHL18" mdate="2019-06-19">
<author pid="92/3836">Shimin Gong</author>
<author pid="07/1951-5">Jing Xu 0005</author>
<author pid="92/2834-1">Lin Gao 0001</author>
<author pid="85/2836">Xiaoxia Huang</author>
<author pid="49/3283-4">Wei Liu 0004</author>
<title>Passive relaying scheme via backscatter communications in cooperative wireless networks.</title>
<pages>1-6</pages>
<year>2018</year>
<booktitle>WCNC</booktitle>
<ee>https://doi.org/10.1109/WCNC.2018.8377075</ee>
<crossref>conf/wcnc/2018</crossref>
<url>db/conf/wcnc/wcnc2018.html#GongXGHL18</url>
</inproceedings>
</r>
<r><article publtype="informal" key="journals/corr/abs-1810-07889" mdate="2019-02-26">
<author pid="07/1951-5">Jing Xu 0005</author>
<author pid="172/5484">Yuze Zou</author>
<author pid="92/3836">Shimin Gong</author>
<author pid="92/2834-1">Lin Gao 0001</author>
<author pid="76/440">Dusit Niyato</author>
<author pid="31/1966">Wenqing Cheng</author>
<title>Robust Transmissions in Wireless Powered Multi-Relay Networks with Chance Interference Constraints.</title>
<year>2018</year>
<volume>abs/1810.07889</volume>
<journal>CoRR</journal>
<ee type="oa">http://arxiv.org/abs/1810.07889</ee>
<url>db/journals/corr/corr1810.html#abs-1810-07889</url>
</article>
</r>
<r><article key="journals/tvt/JinDZHXX17" mdate="2020-06-25">
<author pid="j/RongJin">Rong Jin</author>
<author pid="62/10013">Xianru Du</author>
<author pid="80/1651-1">Kai Zeng 0001</author>
<author pid="72/4826">Liqun Huang</author>
<author pid="150/5664">Laiyuan Xiao</author>
<author pid="07/1951-5">Jing Xu 0005</author>
<title>Delay Analysis of Physical-Layer Key Generation in Dynamic Roadside-to-Vehicle Networks.</title>
<pages>2526-2535</pages>
<year>2017</year>
<volume>66</volume>
<journal>IEEE Trans. Veh. Technol.</journal>
<number>3</number>
<ee>https://doi.org/10.1109/TVT.2016.2582853</ee>
<url>db/journals/tvt/tvt66.html#JinDZHXX17</url>
</article>
</r>
<r><inproceedings key="conf/IEEEcit/LiXLG017" mdate="2018-01-19">
<author pid="137/8316">Jiachen Li</author>
<author pid="07/1951-5">Jing Xu 0005</author>
<author pid="49/3283-4">Wei Liu 0004</author>
<author pid="92/3836">Shimin Gong</author>
<author pid="80/1651-1">Kai Zeng 0001</author>
<title>Robust Optimal Spectrum Patrolling for Passive Monitoring in Cognitive Radio Networks.</title>
<pages>63-68</pages>
<year>2017</year>
<booktitle>CIT</booktitle>
<ee>https://doi.org/10.1109/CIT.2017.63</ee>
<ee>http://doi.ieeecomputersociety.org/10.1109/CIT.2017.63</ee>
<crossref>conf/IEEEcit/2017</crossref>
<url>db/conf/IEEEcit/IEEEcit2017.html#LiXLG017</url>
</inproceedings>
</r>
<r><inproceedings key="conf/IEEEcit/LiMGXHS17" mdate="2018-01-24">
<author pid="137/8316">Jiachen Li</author>
<author pid="206/0346">Yue Mi</author>
<author pid="92/3836">Shimin Gong</author>
<author pid="07/1951-5">Jing Xu 0005</author>
<author pid="85/2836">Xiaoxia Huang</author>
<author pid="74/2905">Yanyan Shen</author>
<title>Cooperative Multi-relay Assisted Multicast Beamforming in Wirelessly Powered Communications.</title>
<pages>69-74</pages>
<year>2017</year>
<booktitle>CIT</booktitle>
<ee>https://doi.org/10.1109/CIT.2017.62</ee>
<ee>http://doi.ieeecomputersociety.org/10.1109/CIT.2017.62</ee>
<crossref>conf/IEEEcit/2017</crossref>
<url>db/conf/IEEEcit/IEEEcit2017.html#LiMGXHS17</url>
</inproceedings>
</r>
<r><inproceedings key="conf/fie/LiuYFXT17" mdate="2018-01-19">
<author pid="49/3283-4">Wei Liu 0004</author>
<author pid="211/4863">Mengling Yu</author>
<author pid="211/5128">Zijian Fan</author>
<author pid="07/1951-5">Jing Xu 0005</author>
<author pid="39/5423">Yuan Tian</author>
<title>Visual attention based evaluation for multiple-choice tests in e-learning applications.</title>
<pages>1-6</pages>
<year>2017</year>
<booktitle>FIE</booktitle>
<ee>https://doi.org/10.1109/FIE.2017.8190633</ee>
<ee>http://doi.ieeecomputersociety.org/10.1109/FIE.2017.8190633</ee>
<crossref>conf/fie/2017</crossref>
<url>db/conf/fie/fie2017.html#LiuYFXT17</url>
</inproceedings>
</r>
<r><inproceedings key="conf/fie/YuXZLC17" mdate="2018-01-19">
<author pid="211/4863">Mengling Yu</author>
<author pid="07/1951-5">Jing Xu 0005</author>
<author pid="160/6081">Jinrong Zhong</author>
<author pid="49/3283-4">Wei Liu 0004</author>
<author pid="31/1966">Wenqing Cheng</author>
<title>Behavior detection and analysis for learning process in classroom environment.</title>
<pages>1-4</pages>
<year>2017</year>
<booktitle>FIE</booktitle>
<ee>https://doi.org/10.1109/FIE.2017.8190635</ee>
<ee>http://doi.ieeecomputersociety.org/10.1109/FIE.2017.8190635</ee>
<crossref>conf/fie/2017</crossref>
<url>db/conf/fie/fie2017.html#YuXZLC17</url>
</inproceedings>
</r>
<r><inproceedings key="conf/globecom/LiXGHW17" mdate="2018-01-25">
<author pid="137/8316">Jiachen Li</author>
<author pid="07/1951-5">Jing Xu 0005</author>
<author pid="92/3836">Shimin Gong</author>
<author pid="85/2836">Xiaoxia Huang</author>
<author pid="37/1304-1">Ping Wang 0001</author>
<title>Robust Radio Mode Selection in Wirelessly Powered Communications with Uncertain Channel Information.</title>
<pages>1-6</pages>
<year>2017</year>
<booktitle>GLOBECOM</booktitle>
<ee>https://doi.org/10.1109/GLOCOM.2017.8254224</ee>
<crossref>conf/globecom/2017</crossref>
<url>db/conf/globecom/globecom2017.html#LiXGHW17</url>
</inproceedings>
</r>
<r><article key="journals/tcyb/YuanYXLZC16" mdate="2020-05-22">
<author pid="67/2268">Wei Yuan</author>
<author pid="16/1184">Xinge You</author>
<author pid="07/1951-5">Jing Xu 0005</author>
<author pid="12/5155">Henry Leung</author>
<author pid="173/9526">Tianhang Zhang</author>
<author orcid="0000-0001-5451-7230" pid="48/4856">Chun Lung Philip Chen</author>
<title>Multiobjective Optimization of Linear Cooperative Spectrum Sensing: Pareto Solutions and Refinement.</title>
<pages>96-108</pages>
<year>2016</year>
<volume>46</volume>
<journal>IEEE Trans. Cybern.</journal>
<number>1</number>
<ee>https://doi.org/10.1109/TCYB.2015.2395412</ee>
<ee>https://www.wikidata.org/entity/Q50942987</ee>
<url>db/journals/tcyb/tcyb46.html#YuanYXLZC16</url>
</article>
</r>
<r><article key="journals/tmc/JinDDZX16" mdate="2018-01-24">
<author pid="j/RongJin">Rong Jin</author>
<author pid="62/10013">Xianru Du</author>
<author pid="147/3430">Zi Deng</author>
<author pid="80/1651-1">Kai Zeng 0001</author>
<author pid="07/1951-5">Jing Xu 0005</author>
<title>Practical Secret Key Agreement for Full-Duplex Near Field Communications.</title>
<pages>938-951</pages>
<year>2016</year>
<volume>15</volume>
<journal>IEEE Trans. Mob. Comput.</journal>
<number>4</number>
<ee>https://doi.org/10.1109/TMC.2015.2434811</ee>
<ee>http://doi.ieeecomputersociety.org/10.1109/TMC.2015.2434811</ee>
<url>db/journals/tmc/tmc15.html#JinDDZX16</url>
</article>
</r>
<r><article key="journals/twc/XuWZLL16" mdate="2020-09-06">
<author pid="07/1951-5">Jing Xu 0005</author>
<author pid="28/7554">Qingsi Wang</author>
<author pid="80/1651-1">Kai Zeng 0001</author>
<author pid="97/5725">Mingyan Liu</author>
<author pid="49/3283-4">Wei Liu 0004</author>
<title>Sniffer Channel Assignment With Imperfect Monitoring for Cognitive Radio Networks.</title>
<pages>1703-1715</pages>
<year>2016</year>
<volume>15</volume>
<journal>IEEE Trans. Wirel. Commun.</journal>
<number>3</number>
<ee>https://doi.org/10.1109/TWC.2015.2495259</ee>
<url>db/journals/twc/twc15.html#XuWZLL16</url>
</article>
</r>
<r><inproceedings key="conf/iccse2/Fan00C16" mdate="2019-10-04">
<author pid="211/5128">Zijian Fan</author>
<author pid="07/1951-5">Jing Xu 0005</author>
<author pid="49/3283-4">Wei Liu 0004</author>
<author pid="31/1966">Wenqing Cheng</author>
<title>Gesture based misbehavior detection in online examination.</title>
<pages>234-238</pages>
<year>2016</year>
<booktitle>ICCSE</booktitle>
<ee>https://doi.org/10.1109/ICCSE.2016.7581586</ee>
<crossref>conf/iccse2/2016</crossref>
<url>db/conf/iccse2/iccse2016.html#Fan00C16</url>
</inproceedings>
</r>
<r><inproceedings key="conf/ictc/ZouLYX16" mdate="2018-06-23">
<author pid="172/5484">Yuze Zou</author>
<author pid="49/3283-4">Wei Liu 0004</author>
<author pid="48/450-37">Yang Yang 0037</author>
<author pid="07/1951-5">Jing Xu 0005</author>
<title>Energy-aware probabilistic forwarding in wireless content-centric networks.</title>
<pages>270-275</pages>
<year>2016</year>
<booktitle>ICTC</booktitle>
<ee>https://doi.org/10.1109/ICTC.2016.7763484</ee>
<crossref>conf/ictc/2016</crossref>
<url>db/conf/ictc/ictc2016.html#ZouLYX16</url>
</inproceedings>
</r>
<r><inproceedings key="conf/lcn/XuLZ16" mdate="2018-01-19">
<author pid="07/1951-5">Jing Xu 0005</author>
<author pid="49/3283-4">Wei Liu 0004</author>
<author pid="80/1651-1">Kai Zeng 0001</author>
<title>Monitoring Multi-Hop Multi-Channel Wireless Networks: Online Sniffer Channel Assignment.</title>
<pages>579-582</pages>
<year>2016</year>
<booktitle>LCN</booktitle>
<ee>https://doi.org/10.1109/LCN.2016.97</ee>
<ee>http://doi.ieeecomputersociety.org/10.1109/LCN.2016.97</ee>
<crossref>conf/lcn/2016</crossref>
<url>db/conf/lcn/lcn2016.html#XuLZ16</url>
</inproceedings>
</r>
<r><inproceedings key="conf/icc/XuZL15" mdate="2018-01-19">
<author pid="07/1951-5">Jing Xu 0005</author>
<author pid="80/1651-1">Kai Zeng 0001</author>
<author pid="49/3283-4">Wei Liu 0004</author>
<title>Online learning for unreliable passive monitoring in multi-channel wireless networks.</title>
<pages>7257-7262</pages>
<year>2015</year>
<booktitle>ICC</booktitle>
<ee>https://doi.org/10.1109/ICC.2015.7249485</ee>
<crossref>conf/icc/2015</crossref>
<url>db/conf/icc/icc2015.html#XuZL15</url>
</inproceedings>
</r>
<r><inproceedings key="conf/ccs/JinDDZX14" mdate="2018-11-06">
<author pid="j/RongJin">Rong Jin</author>
<author pid="62/10013">Xianru Du</author>
<author pid="147/3430">Zi Deng</author>
<author pid="80/1651-1">Kai Zeng 0001</author>
<author pid="07/1951-5">Jing Xu 0005</author>
<title>Practical secret key agreement for full-duplex near field communications.</title>
<pages>217-228</pages>
<year>2014</year>
<booktitle>AsiaCCS</booktitle>
<ee>https://doi.org/10.1145/2590296.2590327</ee>
<crossref>conf/ccs/2014asia</crossref>
<url>db/conf/ccs/asiaccs2014.html#JinDDZX14</url>
</inproceedings>
</r>
<r><inproceedings key="conf/icc/JinDZXX14" mdate="2018-01-24">
<author pid="j/RongJin">Rong Jin</author>
<author pid="62/10013">Xianru Du</author>
<author pid="80/1651-1">Kai Zeng 0001</author>
<author pid="150/5664">Laiyuan Xiao</author>
<author pid="07/1951-5">Jing Xu 0005</author>
<title>Delay analysis of physical layer key generation in multi-user dynamic wireless networks.</title>
<pages>901-906</pages>
<year>2014</year>
<booktitle>ICC</booktitle>
<ee>https://doi.org/10.1109/ICC.2014.6883434</ee>
<crossref>conf/icc/2014</crossref>
<url>db/conf/icc/icc2014.html#JinDZXX14</url>
</inproceedings>
</r>
<r><article key="journals/cn/ChenXYLC13" mdate="2020-02-19">
<author pid="85/2150">Xiaohui Chen</author>
<author pid="07/1951-5">Jing Xu 0005</author>
<author pid="67/2268">Wei Yuan</author>
<author pid="49/3283-4">Wei Liu 0004</author>
<author pid="31/1966">Wenqing Cheng</author>
<title>Channel assignment in heterogeneous multi-radio multi-channel wireless networks: A game theoretic approach.</title>
<pages>3291-3299</pages>
<year>2013</year>
<volume>57</volume>
<journal>Comput. Networks</journal>
<number>17</number>
<ee>https://doi.org/10.1016/j.comnet.2013.07.017</ee>
<url>db/journals/cn/cn57.html#ChenXYLC13</url>
</article>
</r>
<r><inproceedings key="conf/hpcc/XuWLH13" mdate="2018-01-19">
<author pid="07/1951-5">Jing Xu 0005</author>
<author pid="25/9307">Hanbo Wang</author>
<author pid="49/3283-4">Wei Liu 0004</author>
<author orcid="0000-0002-6766-4923" pid="50/6852">Xiaojun Hei</author>
<title>Towards High-Speed Real-Time HTTP Traffic Analysis on the Tilera Many-Core Platform.</title>
<pages>1763-1768</pages>
<year>2013</year>
<booktitle>HPCC/EUC</booktitle>
<ee>https://doi.org/10.1109/HPCC.and.EUC.2013.252</ee>
<crossref>conf/hpcc/2013</crossref>
<url>db/conf/hpcc/hpcc2013.html#XuWLH13</url>
</inproceedings>
</r>
<r><inproceedings key="conf/wcnc/ChenCYLX13" mdate="2018-01-19">
<author pid="85/2150">Xiaohui Chen</author>
<author pid="31/1966">Wenqing Cheng</author>
<author pid="67/2268">Wei Yuan</author>
<author pid="49/3283-4">Wei Liu 0004</author>
<author pid="07/1951-5">Jing Xu 0005</author>
<title>Joint optimization of channel allocation and AP association in variable channel-width WLANs.</title>
<pages>345-350</pages>
<year>2013</year>
<booktitle>WCNC</booktitle>
<ee>https://doi.org/10.1109/WCNC.2013.6554588</ee>
<crossref>conf/wcnc/2013</crossref>
<url>db/conf/wcnc/wcnc2013.html#ChenCYLX13</url>
</inproceedings>
</r>
<r><inproceedings key="conf/wasa/YiZX12" mdate="2018-01-24">
<author pid="117/3369">Shanhe Yi</author>
<author pid="80/1651-1">Kai Zeng 0001</author>
<author pid="07/1951-5">Jing Xu 0005</author>
<title>Secondary User Monitoring in Unslotted Cognitive Radio Networks with Unknown Models.</title>
<pages>648-659</pages>
<year>2012</year>
<booktitle>WASA</booktitle>
<ee>https://doi.org/10.1007/978-3-642-31869-6_56</ee>
<crossref>conf/wasa/2012</crossref>
<url>db/conf/wasa/wasa2012.html#YiZX12</url>
</inproceedings>
</r>
<r><inproceedings key="conf/cis/PengXLCW11" mdate="2018-01-19">
<author pid="41/7760">Kai Peng</author>
<author pid="07/1951-5">Jing Xu 0005</author>
<author pid="49/3283-4">Wei Liu 0004</author>
<author pid="85/2150">Xiaohui Chen</author>
<author pid="96/2744">Jian Wu</author>
<title>Resource Optimization for Uncertain Traffic Demand in Multi-radio Multi-channel Wireless Networks.</title>
<pages>139-143</pages>
<year>2011</year>
<booktitle>CIS</booktitle>
<ee>https://doi.org/10.1109/CIS.2011.39</ee>
<ee>http://doi.ieeecomputersociety.org/10.1109/CIS.2011.39</ee>
<crossref>conf/cis/2011</crossref>
<url>db/conf/cis/cis2011.html#PengXLCW11</url>
</inproceedings>
</r>
<r><inproceedings key="conf/globecom/XiaYCLWX10" mdate="2018-01-19">
<author pid="89/7553">Wenfang Xia</author>
<author pid="67/2268">Wei Yuan</author>
<author pid="31/1966">Wenqing Cheng</author>
<author pid="49/3283-4">Wei Liu 0004</author>
<author pid="32/5536">Shu Wang</author>
<author pid="07/1951-5">Jing Xu 0005</author>
<title>Optimization of Cooperative Spectrum Sensing in Ad-Hoc Cognitive Radio Networks.</title>
<pages>1-5</pages>
<year>2010</year>
<booktitle>GLOBECOM</booktitle>
<ee>https://doi.org/10.1109/GLOCOM.2010.5683600</ee>
<crossref>conf/globecom/2010</crossref>
<url>db/conf/globecom/globecom2010.html#XiaYCLWX10</url>
</inproceedings>
</r>
<coauthors n="51" nc="1">
<co c="0" n="2"><na f="c/Chen:C=_L=_Philip" pid="48/4856">C. L. Philip Chen</na><na>Chun Lung Philip Chen</na></co>
<co c="0"><na f="c/Chen:Wenfan" pid="239/2697">Wenfan Chen</na></co>
<co c="0"><na f="c/Chen:Xiaohui" pid="85/2150">Xiaohui Chen</na></co>
<co c="0"><na f="c/Cheng:Wenqing" pid="31/1966">Wenqing Cheng</na></co>
<co c="0"><na f="d/Deng:Zi" pid="147/3430">Zi Deng</na></co>
<co c="0"><na f="d/Du:Xianru" pid="62/10013">Xianru Du</na></co>
<co c="0"><na f="f/Fan:Zijian" pid="211/5128">Zijian Fan</na></co>
<co c="0"><na f="f/Feng:Shaohan" pid="199/1893">Shaohan Feng</na></co>
<co c="0"><na f="g/Gao_0001:Lin" pid="92/2834-1">Lin Gao 0001</na></co>
<co c="0"><na f="g/Gong:Shimin" pid="92/3836">Shimin Gong</na></co>
<co c="0"><na f="g/Guo:Yuanxiong" pid="93/10800">Yuanxiong Guo</na></co>
<co c="0"><na f="h/Han:Zhu" pid="83/514">Zhu Han</na></co>
<co c="0"><na f="h/Hei:Xiaojun" pid="50/6852">Xiaojun Hei</na></co>
<co c="0"><na f="h/Hoang:Dinh_Thai" pid="37/8852">Dinh Thai Hoang</na></co>
<co c="0"><na f="h/Huang:Liqun" pid="72/4826">Liqun Huang</na></co>
<co c="0"><na f="h/Huang:Xiaoxia" pid="85/2836">Xiaoxia Huang</na></co>
<co c="0"><na f="j/Jin:Rong" pid="j/RongJin">Rong Jin</na></co>
<co c="0"><na f="l/Leung:Henry" pid="12/5155">Henry Leung</na></co>
<co c="0"><na f="l/Li:Chengming" pid="27/4942">Chengming Li</na></co>
<co c="0"><na f="l/Li:Jiachen" pid="137/8316">Jiachen Li</na></co>
<co c="0"><na f="l/Liang:Ying=Chang" pid="98/153">Ying-Chang Liang</na></co>
<co c="0"><na f="l/Liu:Mingyan" pid="97/5725">Mingyan Liu</na></co>
<co c="0"><na f="l/Liu_0004:Wei" pid="49/3283-4">Wei Liu 0004</na></co>
<co c="0"><na f="l/Luo:Xi" pid="69/7449">Xi Luo</na></co>
<co c="0"><na f="m/Mi:Yue" pid="206/0346">Yue Mi</na></co>
<co c="0"><na f="n/Niyato:Dusit" pid="76/440">Dusit Niyato</na></co>
<co c="0"><na f="p/Peng:Kai" pid="41/7760">Kai Peng</na></co>
<co c="0"><na f="s/Shen:Yanyan" pid="74/2905">Yanyan Shen</na></co>
<co c="0"><na f="t/Tian:Yuan" pid="39/5423">Yuan Tian</na></co>
<co c="0"><na f="w/Wang:Hanbo" pid="25/9307">Hanbo Wang</na></co>
<co c="0"><na f="w/Wang_0001:Ping" pid="37/1304-1">Ping Wang 0001</na></co>
<co c="0"><na f="w/Wang:Qingsi" pid="28/7554">Qingsi Wang</na></co>
<co c="0"><na f="w/Wang:Shu" pid="32/5536">Shu Wang</na></co>
<co c="0"><na f="w/Wang:Yi" pid="17/221">Yi Wang</na></co>
<co c="0"><na f="w/Wu:Jian" pid="96/2744">Jian Wu</na></co>
<co c="0"><na f="x/Xia:Wenfang" pid="89/7553">Wenfang Xia</na></co>
<co c="0"><na f="x/Xiao:Laiyuan" pid="150/5664">Laiyuan Xiao</na></co>
<co c="0"><na f="x/Xie:Yutong" pid="187/0165">Yutong Xie</na></co>
<co c="0"><na f="x/Xu_0005:Wenbo" pid="81/4590-5">Wenbo Xu 0005</na></co>
<co c="0"><na f="x/Xu:Zhengzhuo" pid="250/1076">Zhengzhuo Xu</na></co>
<co c="0"><na f="y/Yang_0037:Yang" pid="48/450-37">Yang Yang 0037</na></co>
<co c="0"><na f="y/Yi:Shanhe" pid="117/3369">Shanhe Yi</na></co>
<co c="0"><na f="y/You:Xinge" pid="16/1184">Xinge You</na></co>
<co c="0"><na f="y/Yu:Mengling" pid="211/4863">Mengling Yu</na></co>
<co c="0"><na f="y/Yuan:Wei" pid="67/2268">Wei Yuan</na></co>
<co c="0"><na f="z/Zeng_0001:Kai" pid="80/1651-1">Kai Zeng 0001</na></co>
<co c="0"><na f="z/Zhang:Tianhang" pid="173/9526">Tianhang Zhang</na></co>
<co c="0"><na f="z/Zhong:Jinrong" pid="160/6081">Jinrong Zhong</na></co>
<co c="0"><na f="z/Zhong:Yuxing" pid="250/1069">Yuxing Zhong</na></co>
<co c="0"><na f="z/Zhu_0001:Kun" pid="95/1161-1">Kun Zhu 0001</na></co>
<co c="0"><na f="z/Zou:Yuze" pid="172/5484">Yuze Zou</na></co>
</coauthors>
</dblpperson>

